stringmanipulate/Stringmanipulate.py
stringmanipulate/__init__.py
stringmanipulate/__main__.py
stringmanipulate-0.0.3.dist-info/METADATA
stringmanipulate-0.0.3.dist-info/WHEEL
stringmanipulate-0.0.3.dist-info/entry_points.txt
stringmanipulate-0.0.3.dist-info/licenses/LICENSE
stringmanipulate-0.0.3.dist-info/RECORD
